{
	"@metadata": {
		"authors": [
			"C.R."
		]
	},
	"wikimediamessages-desc": "Mmasciate specifiche a tiempo curto Wikimedia",
	"bug-54847-password-reset-prompt": "Pe' bbìa 'e nu [[meta:October 2013 private data security issue|probblema 'e sicurezza ch' 'e database 'e Wikimedia Labs]], 'e password ausàte apprimma putessero stà a vulnerabbiletà. Pe' piacere mpustate na password nuova nuova pe' puté garantí l'utenza vuosta. Scusatece 'e st'inconveniente.",
	"password-recycled": "'A password nzertàta currisponne a na vecchia password suoccia a ll'utenza vuosta. Pe' piacere mpustate na password nuova",
	"grouppage-oversight": "{{ns:project}}:Oversight",
	"group-oversight": "Oversighter",
	"group-oversight-member": "oversight",
	"please-translate": "Aiutatece a traducere dint' 'a lengua vosta"
}
